MANIFEST.in
README.md
setup.cfg
setup.py
versioneer.py
pyqtinstaller/__init__.py
pyqtinstaller/_version.py
pyqtinstaller/compile_command.py
pyqtinstaller/package.pdy.jinja
pyqtinstaller/resources.qrc.jinja
pyqtinstaller/setup.iss.jinja
pyqtinstaller.egg-info/PKG-INFO
pyqtinstaller.egg-info/SOURCES.txt
pyqtinstaller.egg-info/dependency_links.txt
pyqtinstaller.egg-info/entry_points.txt
pyqtinstaller.egg-info/requires.txt
pyqtinstaller.egg-info/top_level.txt