Metadata-Version: 2.1
Name: pyqtinstaller
Version: 0.2.10
Summary: A toolkit for PyQt 5
Home-page: https://github.com/Simmovation/pyqtinstaller
Author: Simmovation Ltd
Author-email: info@simmovation.tech
License: GPLv3
Platform: any
Requires-Python: ==3.6.*
Provides-Extra: test
Provides-Extra: publish
